{
  "_schema": {
    "labels": {
      "module": "Module",
      "key": "Key",
      "value": "Item"
    }
  },
  "system": {
    "name": "Michael DaSilva",
    "email": "ukemkr@gmail.com",
    "company": "DaSilva Ukulele Co.",
    "title": "Engineer",
    "street": "2547 8th St. STE 28",
    "city": "BERKELEY",
    "state": "CA",
    "phone": "5108598532",
    "activeProjectName": "Development System"
  },
  "projects": {
    "PocketDRO": {
      "startDate": "2025-07-05",
      "endDate": "2025-07-17",
      "status": "Not Started"
    },
    "Development System": {
      "startDate": "2025-07-25",
      "endDate": "2025-07-08",
      "status": "On Hold"
    }
  }
}